odoo8_addon_partner_identification_gln-8.0.1.0.0-py2.7-nspkg.pth
odoo8_addon_partner_identification_gln-8.0.1.0.0.dist-info/DESCRIPTION.rst
odoo8_addon_partner_identification_gln-8.0.1.0.0.dist-info/METADATA
odoo8_addon_partner_identification_gln-8.0.1.0.0.dist-info/RECORD
odoo8_addon_partner_identification_gln-8.0.1.0.0.dist-info/WHEEL
odoo8_addon_partner_identification_gln-8.0.1.0.0.dist-info/metadata.json
odoo8_addon_partner_identification_gln-8.0.1.0.0.dist-info/namespace_packages.txt
odoo8_addon_partner_identification_gln-8.0.1.0.0.dist-info/top_level.txt
odoo_addons/partner_identification_gln/README.rst
odoo_addons/partner_identification_gln/__init__.py
odoo_addons/partner_identification_gln/__openerp__.py
odoo_addons/partner_identification_gln/data/partner_identification_gln.xml
odoo_addons/partner_identification_gln/models/__init__.py
odoo_addons/partner_identification_gln/models/partner.py
odoo_addons/partner_identification_gln/static/description/icon.svg
odoo_addons/partner_identification_gln/tests/__init__.py
odoo_addons/partner_identification_gln/tests/test_gln.py
