Metadata-Version: 2.0
Name: odoo8-addon-partner-identification-gln
Version: 8.0.1.0.0
Summary: This addon extends "Partner Identification Numbers"
Home-page: https://www.acsone.eu
Author: Acsone S.A.,Odoo Community Association (OCA)
Author-email: support@odoo-community.org
License: AGPL-3
Platform: UNKNOWN
Classifier: Programming Language :: Python :: 2.7
Classifier: Framework :: Odoo
Classifier: License :: OSI Approved :: GNU Affero General Public License v3
Requires-Dist: odoo (<9.0a,>=8.0a)
Requires-Dist: odoo8-addon-partner-identification
Requires-Dist: python-stdnum
